endnote_generator/__init__.py
endnote_generator/endnote_writer.py
endnote_generator/library_manager.py
endnote_generator/metadata_fetcher.py
endnote_generator/pdf_processor.py
endnote_generator-0.1.0.dist-info/METADATA
endnote_generator-0.1.0.dist-info/WHEEL
endnote_generator-0.1.0.dist-info/top_level.txt
endnote_generator-0.1.0.dist-info/RECORD
