Metadata-Version: 2.4
Name: endnote-generator
Version: 0.1.0
Summary: A tool to generate EndNote XML libraries from PDF files using DOI metadata.
Author-email: Mohamed Elnahla <mohamed.elnahla.2@gmail.com>
Project-URL: Homepage, https://github.com/Mohamed-Elnahla/Endnote-Library-Generator
Project-URL: Bug Tracker, https://github.com/Mohamed-Elnahla/Endnote-Library-Generator/issues
Classifier: Programming Language :: Python :: 3
Classifier: License :: OSI Approved :: MIT License
Classifier: Operating System :: OS Independent
Requires-Python: >=3.8
Requires-Dist: PyMuPDF>=1.26.7
Requires-Dist: requests
Requires-Dist: pandas>=2.0.0
